{
  "topic_id": "HR0011SB20254XL-01",
  "title": "ALIAS Missionized Autonomy for Emergency Services",
  "repo_name": "HR0011SB20254XL-01-ALIAS-Emergency-Assurance",
  "generated_at_utc": "2026-05-03T04:54:35Z",
  "git_head": "UNCOMMITTED_SCAFFOLD",
  "scenarios_total": 3,
  "scenarios_passed": 3,
  "pass_rate_pct": 100.0,
  "evidence_type": "deterministic synthetic autonomy traces for submission-stage feasibility review",
  "entries": [
    {
      "id": "scenario_01_nominal_response_leg",
      "label": "Nominal Fireline Recon Leg",
      "mode": "nominal",
      "expected": "No flags or rejects; trust should remain near 1.0.",
      "observed": "accept=60, flag=0, reject=0, final_trust=1.000",
      "passed": true,
      "scorecard_path": "evidence/scenario_01_nominal_response_leg/trust_scorecard.json",
      "timeline_path": "evidence/scenario_01_nominal_response_leg/timeline.json",
      "proof_log_path": "evidence/scenario_01_nominal_response_leg/proof_log.txt",
      "trace_path": "evidence/scenario_01_nominal_response_leg/trace.svg",
      "accept_frames": 60,
      "flag_frames": 0,
      "reject_frames": 0,
      "final_trust_score": 1.0,
      "first_reject_frame": null
    },
    {
      "id": "scenario_02_hazard_compression",
      "label": "Smoke Corridor Compression",
      "mode": "degraded",
      "expected": "Flags should appear without hard rejects; trust should decline but remain above failure.",
      "observed": "accept=30, flag=30, reject=0, final_trust=0.427",
      "passed": true,
      "scorecard_path": "evidence/scenario_02_hazard_compression/trust_scorecard.json",
      "timeline_path": "evidence/scenario_02_hazard_compression/timeline.json",
      "proof_log_path": "evidence/scenario_02_hazard_compression/proof_log.txt",
      "trace_path": "evidence/scenario_02_hazard_compression/trace.svg",
      "accept_frames": 30,
      "flag_frames": 30,
      "reject_frames": 0,
      "final_trust_score": 0.4269998,
      "first_reject_frame": null
    },
    {
      "id": "scenario_03_unrecoverable_emergency_path",
      "label": "Unrecoverable Fireline Divert",
      "mode": "fault",
      "expected": "Reject behavior should appear with a deterministic first reject frame.",
      "observed": "accept=20, flag=0, reject=40, first_reject=20, final_trust=0.000",
      "passed": true,
      "scorecard_path": "evidence/scenario_03_unrecoverable_emergency_path/trust_scorecard.json",
      "timeline_path": "evidence/scenario_03_unrecoverable_emergency_path/timeline.json",
      "proof_log_path": "evidence/scenario_03_unrecoverable_emergency_path/proof_log.txt",
      "trace_path": "evidence/scenario_03_unrecoverable_emergency_path/trace.svg",
      "accept_frames": 20,
      "flag_frames": 0,
      "reject_frames": 40,
      "final_trust_score": 0.0,
      "first_reject_frame": 20
    }
  ]
}
